setup.py
client/__init__.py
client/client.py
client/chat_tests/__init__.py
client/chat_tests/client_tests.py
client/chat_tests/server_tests.py
client/chat_tests/utils_tests.py
client/client/__init__.py
client/client/client_db.py
client/client/client_gui.py
client/client/contact_add.py
client/client/del_contact.py
client/client/main_window_gui.py
client/client/start_dialog.py
client/client/transport.py
client/common/__init__.py
client/common/decos_logging.py
client/common/descriptors.py
client/common/metacls.py
client/common/utils.py
client/logs/__init__.py
client/logs/client_log_config.py
client/logs/server_log_config.py
client_messager_proj.egg-info/PKG-INFO
client_messager_proj.egg-info/SOURCES.txt
client_messager_proj.egg-info/dependency_links.txt
client_messager_proj.egg-info/requires.txt
client_messager_proj.egg-info/top_level.txt