Metadata-Version: 1.0
Name: client-messager-proj
Version: 0.9.1
Summary: client_messager_proj
Home-page: UNKNOWN
Author: Vovk Vladislav
Author-email: vovkvladyslav@yandex.ru
License: UNKNOWN
Platform: UNKNOWN
